Workbook
Name aporte: APP!$D$19
Name patrimonio: APP!$D$22
Name qtd_anos: APP!$D$20
Name rendimento_carteira: APP!$D$15
Name salario: APP!$D$14
Name sugestao_rendimento: APP!$D$16
Name taxa_mensal: APP!$D$21

Sheet APP
B13: CONFIGURAÇÕES
B14: Salário | D14: 2000
B15: Rendimento Carteira | D15: 0.006
B16: Sugestão de Investimento (30%) | D16: =D14*30% -> 600
B18: INVESTIMENTO MENSAL
B19: Quanto investir por mês? | D19: 200
B20: Por quantos anos? | D20: 5
B21: Taxa de Rendimento mensal? | D21: 0.01079
B22: Patrimônio acumulado? | D22: =FV(taxa_mensal,qtd_anos*12,aporte*-1) -> 16755.383
B23: Dividendos mensais? | D23: =patrimonio*rendimento_carteira -> 100.5323
B25: CENÁRIOS | D25: DIVIDENDO
A26: 2 | B26: Quanto em 2 anos? | C26: =FV($D$21,$A26*12,$D$19*-1) -> 5445.5255 | D26: =C26*rendimento_carteira -> 32.673153
A27: 5 | B27: Quanto em 5 anos? | C27: =FV($D$21,$A27*12,$D$19*-1) -> 16755.383 | D27: =C27*rendimento_carteira -> 100.5323
A28: 10 | B28: Quanto em 10 anos? | C28: =FV($D$21,$A28*12,$D$19*-1) -> 48656.843 | D28: =C28*rendimento_carteira -> 291.94106
A29: 20 | B29: Quanto em 20 anos? | C29: =FV($D$21,$A29*12,$D$19*-1) -> 225039.68 | D29: =C29*rendimento_carteira -> 1350.2381
A30: 30 | B30: Quanto em 30 anos? | C30: =FV($D$21,$A30*12,$D$19*-1) -> 864433.93 | D30: =C30*rendimento_carteira -> 5186.6036
B32: PERFIL | D32: MODERADO
B33: VALOR A SER INVESTIDO POR MÊS | D33: =aporte -> 200
B35: TIPO DE FII | C35: PERCENTUAL SUGERIDO | D35: VALORES
B36: PAPEL | C36: =VLOOKUP($D$32&"-"&B36,CHAVE!$A:$D,4,FALSE) -> 0.4 | D36: =aporte*C36 -> 80
B37: TIJOLO | C37: =VLOOKUP($D$32&"-"&B37,CHAVE!$A:$D,4,FALSE) -> 0.2 | D37: =aporte*C37 -> 40
B38: HÍBRIDO | C38: =VLOOKUP($D$32&"-"&B38,CHAVE!$A:$D,4,FALSE) -> 0.15 | D38: =aporte*C38 -> 30
B39: FOFs | C39: =VLOOKUP($D$32&"-"&B39,CHAVE!$A:$D,4,FALSE) -> 0.15 | D39: =aporte*C39 -> 30
B40: DESENVOLVIMENTO | C40: =VLOOKUP($D$32&"-"&B40,CHAVE!$A:$D,4,FALSE) -> 0.05 | D40: =aporte*C40 -> 10
B41: HOTELARIAS | C41: =VLOOKUP($D$32&"-"&B41,CHAVE!$A:$D,4,FALSE) -> 0.05 | D41: =aporte*C41 -> 10
D42: =SUM(D36:D41) -> 200

Sheet CHAVE
A2: CHAVE | B2: PERFIL | C2: TIPO DE FII | D2: % | F2: =A3 -> CONSERVADOR-PAPEL | G2: =VLOOKUP(F2,$A:$D,4,FALSE) -> 0.3
A3: =B3&"-"&C3 -> CONSERVADOR-PAPEL | B3: CONSERVADOR | C3: PAPEL | D3: 0.3
A4: =B4&"-"&C4 -> CONSERVADOR-TIJOLO | B4: CONSERVADOR | C4: TIJOLO | D4: 0.2
A5: =B5&"-"&C5 -> CONSERVADOR-HÍBRIDO | B5: CONSERVADOR | C5: HÍBRIDO | D5: 0.2
A6: =B6&"-"&C6 -> CONSERVADOR-FOFs | B6: CONSERVADOR | C6: FOFs | D6: 0.15
A7: =B7&"-"&C7 -> CONSERVADOR-DESENVOLVIMENTO | B7: CONSERVADOR | C7: DESENVOLVIMENTO | D7: 0.1
A8: =B8&"-"&C8 -> CONSERVADOR-HOTELARIAS | B8: CONSERVADOR | C8: HOTELARIAS | D8: 0.05
A9: =B9&"-"&C9 -> MODERADO-PAPEL | B9: MODERADO | C9: PAPEL | D9: 0.4
A10: =B10&"-"&C10 -> MODERADO-TIJOLO | B10: MODERADO | C10: TIJOLO | D10: 0.2
A11: =B11&"-"&C11 -> MODERADO-HÍBRIDO | B11: MODERADO | C11: HÍBRIDO | D11: 0.15
A12: =B12&"-"&C12 -> MODERADO-FOFs | B12: MODERADO | C12: FOFs | D12: 0.15
A13: =B13&"-"&C13 -> MODERADO-DESENVOLVIMENTO | B13: MODERADO | C13: DESENVOLVIMENTO | D13: 0.05
A14: =B14&"-"&C14 -> MODERADO-HOTELARIAS | B14: MODERADO | C14: HOTELARIAS | D14: 0.05
... A20: =B20&"-"&C20 -> AGRESSIVO-HOTELARIAS | B20: AGRESSIVO | C20: HOTELARIAS | D20: 0.1
